fernbase/__init__.py
fernbase/example.py
fernbase-0.0.1.dist-info/METADATA
fernbase-0.0.1.dist-info/WHEEL
fernbase-0.0.1.dist-info/licenses/LICENSE
fernbase-0.0.1.dist-info/RECORD
